{"different":{"different":{"currentVault":{"count":31,"lastUpdated":1744774987717}}},"believe":{"believe":{"currentVault":{"count":33,"lastUpdated":1743518591642}}},"language":{"language":{"currentVault":{"count":13,"lastUpdated":1744775721356}}},"context":{"context":{"currentVault":{"count":8,"lastUpdated":1742954919366}}},"property":{"property":{"currentVault":{"count":20,"lastUpdated":1743908746963}}},"theory":{"theory":{"currentVault":{"count":16,"lastUpdated":1743522694564}}},"Definition":{"Definition":{"currentVault":{"count":8,"lastUpdated":1743526310940}}},"directly":{"directly":{"currentVault":{"count":6,"lastUpdated":1742960437333}}},"proposition":{"proposition":{"currentVault":{"count":64,"lastUpdated":1743910795569}}},"motivation":{"motivation":{"currentVault":{"count":8,"lastUpdated":1743561390528}}},"relation":{"relation":{"currentVault":{"count":40,"lastUpdated":1743211818231}}},"elements":{"elements":{"currentVault":{"count":7,"lastUpdated":1742952259062}}},"Proposition":{"Proposition":{"currentVault":{"count":12,"lastUpdated":1743918153758}}},"transitive":{"transitive":{"currentVault":{"count":5,"lastUpdated":1743888515009}}},"Therefore":{"Therefore":{"currentVault":{"count":115,"lastUpdated":1744776132099}}},"science":{"science":{"currentVault":{"count":2,"lastUpdated":1742962503875}}},"knowledge":{"knowledge":{"currentVault":{"count":30,"lastUpdated":1742954255122}}},"restriction":{"restriction":{"currentVault":{"count":9,"lastUpdated":1742599124790}}},"possible":{"possible":{"currentVault":{"count":32,"lastUpdated":1743536912443}}},"important":{"important":{"currentVault":{"count":8,"lastUpdated":1742962219206}}},"Transitivity":{"Transitivity":{"currentFile":{"count":5,"lastUpdated":1742246930128}}},"asymmetric":{"asymmetric":{"currentVault":{"count":4,"lastUpdated":1742604578829}}},"assumption":{"assumption":{"currentVault":{"count":14,"lastUpdated":1743533008185}}},"define":{"define":{"currentVault":{"count":7,"lastUpdated":1742614622989}}},"definition":{"definition":{"currentVault":{"count":18,"lastUpdated":1743916774534}}},"analyze":{"analyze":{"currentVault":{"count":1,"lastUpdated":1743893373931}}},"example":{"example":{"currentVault":{"count":16,"lastUpdated":1743519142012}}},"exactly":{"exactly":{"currentVault":{"count":4,"lastUpdated":1743469253961}}},"constructed":{"constructed":{"currentVault":{"count":3,"lastUpdated":1742957807267}}},"already":{"already":{"currentVault":{"count":3,"lastUpdated":1743388495724}}},"develop":{"develop":{"currentVault":{"count":7,"lastUpdated":1742950301739}}},"philosophy":{"philosophy":{"currentVault":{"count":2,"lastUpdated":1742608086381}}},"observable":{"observable":{"currentFile":{"count":34,"lastUpdated":1743609186981}}},"problem":{"problem":{"currentVault":{"count":25,"lastUpdated":1743472045917}}},"phenomena":{"phenomena":{"currentVault":{"count":11,"lastUpdated":1742955896719}}},"structure":{"structure":{"currentVault":{"count":69,"lastUpdated":1743908711955}}},"statement":{"statement":{"currentVault":{"count":10,"lastUpdated":1743000832504}}},"pragmatic":{"pragmatic":{"currentVault":{"count":14,"lastUpdated":1742996881566}}},"epistemic":{"epistemic":{"currentVault":{"count":5,"lastUpdated":1743609228405}}},"explanation":{"explanation":{"currentVault":{"count":147,"lastUpdated":1743561416894}}},"vocabulary":{"vocabulary":{"currentVault":{"count":2,"lastUpdated":1743012164510}}},"obviously":{"obviously":{"currentVault":{"count":8,"lastUpdated":1743893421705}}},"Contradiction":{"Contradiction":{"currentVault":{"count":7,"lastUpdated":1743463873168}}},"reductio":{"reductio":{"currentVault":{"count":15,"lastUpdated":1743463954957}}},"Obviously":{"Obviously":{"currentVault":{"count":2,"lastUpdated":1743464143338}}},"relative":{"relative":{"currentVault":{"count":10,"lastUpdated":1742597341863}}},"connect":{"connect":{"currentVault":{"count":6,"lastUpdated":1743025894878}}},"Similarly":{"Similarly":{"currentVault":{"count":8,"lastUpdated":1742945906283}}},"infinite":{"infinite":{"currentVault":{"count":20,"lastUpdated":1743559036440}}},"because":{"because":{"currentVault":{"count":75,"lastUpdated":1744775714427}}},"position":{"position":{"currentVault":{"count":7,"lastUpdated":1743536400961}}},"Different":{"Different":{"currentVault":{"count":6,"lastUpdated":1743200574228}}},"Theorem":{"Theorem":{"currentVault":{"count":4,"lastUpdated":1742857707830}}},"hypothesis":{"hypothesis":{"currentVault":{"count":9,"lastUpdated":1743908383956}}},"explain":{"explain":{"currentVault":{"count":27,"lastUpdated":1743525360287}}},"argument":{"argument":{"currentVault":{"count":49,"lastUpdated":1743532999571}}},"conclusion":{"conclusion":{"currentVault":{"count":12,"lastUpdated":1742958599338}}},"background":{"background":{"currentVault":{"count":7,"lastUpdated":1743119818457}}},"information":{"information":{"currentVault":{"count":20,"lastUpdated":1743036636314}}},"between":{"between":{"currentVault":{"count":22,"lastUpdated":1743025645001}}},"Solution":{"Solution":{"currentVault":{"count":2,"lastUpdated":1742441462227}}},"relevant":{"relevant":{"currentVault":{"count":6,"lastUpdated":1743217687215}}},"interest":{"interest":{"currentVault":{"count":3,"lastUpdated":1742952250065}}},"explanatory":{"explanatory":{"currentVault":{"count":105,"lastUpdated":1743561100845}}},"whatever":{"whatever":{"currentVault":{"count":5,"lastUpdated":1743559042427}}},"action":{"action":{"currentFile":{"count":8,"lastUpdated":1743017677275}}},"accept":{"accept":{"currentVault":{"count":9,"lastUpdated":1743038103063}}},"consistent":{"consistent":{"currentVault":{"count":17,"lastUpdated":1743893433122}}},"sufficient":{"sufficient":{"currentVault":{"count":8,"lastUpdated":1743520906864}}},"Explanatory":{"Explanatory":{"currentFile":{"count":9,"lastUpdated":1743471148124},"currentVault":{"count":2,"lastUpdated":1742610237595}}},"success":{"success":{"currentVault":{"count":6,"lastUpdated":1743217658845}}},"Objection":{"Objection":{"currentFile":{"count":32,"lastUpdated":1743536538338}}},"principle":{"principle":{"currentVault":{"count":17,"lastUpdated":1744776000007}}},"complete":{"complete":{"currentFile":{"count":15,"lastUpdated":1743520220212}}},"construct":{"construct":{"currentFile":{"count":16,"lastUpdated":1743916573968}}},"method":{"method":{"currentVault":{"count":4,"lastUpdated":1742944855523}}},"arbitrary":{"arbitrary":{"currentVault":{"count":24,"lastUpdated":1743915956878}}},"compatible":{"compatible":{"currentVault":{"count":3,"lastUpdated":1743211501770}}},"difference":{"difference":{"currentVault":{"count":4,"lastUpdated":1744775063800}}},"everything":{"everything":{"currentVault":{"count":18,"lastUpdated":1743536869674}}},"quantum":{"quantum":{"currentVault":{"count":1,"lastUpdated":1743471392832}}},"something":{"something":{"currentVault":{"count":7,"lastUpdated":1743518331431}}},"exist":{"exist":{"currentFile":{"count":3,"lastUpdated":1742601075894}}},"exists":{"exists":{"currentFile":{"count":15,"lastUpdated":1744775833829}}},"Explanation":{"Explanation":{"currentFile":{"count":28,"lastUpdated":1743438539594}}},"appropriate":{"appropriate":{"currentVault":{"count":19,"lastUpdated":1742959936298}}},"response":{"response":{"currentVault":{"count":2,"lastUpdated":1742949994579}}},"Problem":{"Problem":{"currentVault":{"count":25,"lastUpdated":1744776398674}}},"irrelevant":{"irrelevant":{"currentVault":{"count":7,"lastUpdated":1743119402473}}},"embedded":{"embedded":{"currentVault":{"count":1,"lastUpdated":1742429918558}}},"physical":{"physical":{"currentFile":{"count":4,"lastUpdated":1743115721530}}},"Defense":{"Defense":{"currentFile":{"count":14,"lastUpdated":1743561193484}}},"equivalent":{"equivalent":{"currentVault":{"count":9,"lastUpdated":1743916688715}}},"distinguish":{"distinguish":{"currentVault":{"count":9,"lastUpdated":1743520817068}}},"syntactic":{"syntactic":{"currentVault":{"count":5,"lastUpdated":1743014361677}}},"specify":{"specify":{"currentVault":{"count":4,"lastUpdated":1743013220708}}},"sentences":{"sentences":{"currentVault":{"count":23,"lastUpdated":1743891175309}}},"particular":{"particular":{"currentVault":{"count":12,"lastUpdated":1743471322206}}},"objective":{"objective":{"currentVault":{"count":3,"lastUpdated":1742437051005}}},"correct":{"correct":{"currentVault":{"count":11,"lastUpdated":1742948180447}}},"commit":{"commit":{"currentVault":{"count":7,"lastUpdated":1743210896368}}},"commitments":{"commitments":{"currentVault":{"count":19,"lastUpdated":1742435240096}}},"woman":{"woman":{"currentVault":{"count":2,"lastUpdated":1742343964054}}},"framework":{"framework":{"currentVault":{"count":7,"lastUpdated":1742614031263}}},"cannot":{"cannot":{"currentVault":{"count":36,"lastUpdated":1743533070012}}},"according":{"according":{"currentVault":{"count":4,"lastUpdated":1743206552092}}},"perfect":{"perfect":{"currentVault":{"count":2,"lastUpdated":1742340454884}}},"right":{"right":{"currentFile":{"count":6,"lastUpdated":1743000133957}}},"fully":{"fully":{"currentVault":{"count":6,"lastUpdated":1743523092619}}},"require":{"require":{"currentVault":{"count":22,"lastUpdated":1743202212678}}},"psychology":{"psychology":{"currentVault":{"count":4,"lastUpdated":1743115726147}}},"collapse":{"collapse":{"currentVault":{"count":3,"lastUpdated":1743560939165}}},"describe":{"describe":{"currentVault":{"count":12,"lastUpdated":1743027467101}}},"fundamental":{"fundamental":{"currentVault":{"count":63,"lastUpdated":1743561393038}}},"result":{"result":{"currentVault":{"count":8,"lastUpdated":1743033307554}}},"guarantee":{"guarantee":{"currentVault":{"count":2,"lastUpdated":1742948233486}}},"completely":{"completely":{"currentVault":{"count":6,"lastUpdated":1742598861567}}},"plausible":{"plausible":{"currentVault":{"count":18,"lastUpdated":1743558764026}}},"languages":{"languages":{"currentVault":{"count":28,"lastUpdated":1742597339554}}},"distinct":{"distinct":{"currentVault":{"count":20,"lastUpdated":1743609233428}}},"generalization":{"generalization":{"currentVault":{"count":4,"lastUpdated":1742429938793}}},"possibility":{"possibility":{"currentVault":{"count":6,"lastUpdated":1743559630831}}},"solution":{"solution":{"currentVault":{"count":11,"lastUpdated":1743040260002}}},"totality":{"totality":{"currentVault":{"count":3,"lastUpdated":1743219946260}}},"conjunction":{"conjunction":{"currentVault":{"count":25,"lastUpdated":1742956687085}}},"supervenience":{"supervenience":{"currentVault":{"count":7,"lastUpdated":1742342825508}}},"Fundamentally":{"Fundamentally":{"currentVault":{"count":4,"lastUpdated":1742597366608}}},"Fundamentality":{"Fundamentality":{"currentFile":{"count":8,"lastUpdated":1743461858148}}},"methodology":{"methodology":{"currentVault":{"count":8,"lastUpdated":1743039955622}}},"necessary":{"necessary":{"currentVault":{"count":24,"lastUpdated":1744775811155}}},"determinable":{"determinable":{"currentVault":{"count":6,"lastUpdated":1742440977531}}},"necessity":{"necessity":{"currentVault":{"count":13,"lastUpdated":1744775808460}}},"Feature":{"Feature":{"currentVault":{"count":4,"lastUpdated":1743536729943}}},"fundamentality":{"fundamentality":{"currentFile":{"count":11,"lastUpdated":1743220828759},"currentVault":{"count":1,"lastUpdated":1743367340406}}},"incomplete":{"incomplete":{"currentVault":{"count":9,"lastUpdated":1743220778342}}},"Remark":{"Remark":{"currentVault":{"count":2,"lastUpdated":1742341480879}}},"subject":{"subject":{"currentVault":{"count":17,"lastUpdated":1742340405298}}},"themselves":{"themselves":{"currentVault":{"count":6,"lastUpdated":1743471473869}}},"Example":{"Example":{"currentVault":{"count":4,"lastUpdated":1743212291707}}},"himself":{"himself":{"currentVault":{"count":8,"lastUpdated":1742998483518}}},"satisfy":{"satisfy":{"currentVault":{"count":17,"lastUpdated":1743908733246}}},"explanan":{"explanan":{"currentVault":{"count":5,"lastUpdated":1743037125130}}},"object":{"object":{"currentVault":{"count":20,"lastUpdated":1744774125553}}},"except":{"except":{"currentVault":{"count":5,"lastUpdated":1743916188931}}},"following":{"following":{"currentVault":{"count":15,"lastUpdated":1743038080169}}},"explaining":{"explaining":{"currentVault":{"count":8,"lastUpdated":1743012183410}}},"understand":{"understand":{"currentVault":{"count":6,"lastUpdated":1743521688744}}},"account":{"account":{"currentVault":{"count":27,"lastUpdated":1743471119594}}},"similar":{"similar":{"currentVault":{"count":5,"lastUpdated":1743520872163}}},"Possible":{"Possible":{"currentVault":{"count":2,"lastUpdated":1742441458557}}},"necessarily":{"necessarily":{"currentVault":{"count":7,"lastUpdated":1744775828920}}},"cognitive":{"cognitive":{"currentVault":{"count":3,"lastUpdated":1742437083926}}},"Alternative":{"Alternative":{"currentVault":{"count":7,"lastUpdated":1743523255650}}},"agreement":{"agreement":{"currentVault":{"count":2,"lastUpdated":1742430512027}}},"Preliminary":{"Preliminary":{"currentVault":{"count":4,"lastUpdated":1742429978056}}},"uniquely":{"uniquely":{"currentVault":{"count":11,"lastUpdated":1742599108173}}},"restrict":{"restrict":{"currentVault":{"count":3,"lastUpdated":1743011344581}}},"individual":{"individual":{"currentVault":{"count":4,"lastUpdated":1743520904606}}},"reliable":{"reliable":{"currentVault":{"count":4,"lastUpdated":1742944545255}}},"yourself":{"yourself":{"currentVault":{"count":4,"lastUpdated":1743119452132}}},"analysis":{"analysis":{"currentVault":{"count":4,"lastUpdated":1743470847455}}},"therefore":{"therefore":{"currentFile":{"count":8,"lastUpdated":1742610046448},"currentVault":{"count":6,"lastUpdated":1743890308131}}},"collection":{"collection":{"currentVault":{"count":6,"lastUpdated":1743528813409}}},"valid":{"valid":{"currentVault":{"count":3,"lastUpdated":1742959367661}}},"semantic":{"semantic":{"currentVault":{"count":9,"lastUpdated":1743014358124}}},"deductive":{"deductive":{"currentVault":{"count":7,"lastUpdated":1742959363234}}},"constant":{"constant":{"currentVault":{"count":26,"lastUpdated":1743915798131}}},"formula":{"formula":{"currentFile":{"count":68,"lastUpdated":1743388558686}}},"predicate":{"predicate":{"currentFile":{"count":9,"lastUpdated":1742435400840}}},"Aristotle":{"Aristotle":{"currentVault":{"count":6,"lastUpdated":1742667143403}}},"inference":{"inference":{"currentVault":{"count":5,"lastUpdated":1743901546320}}},"Unification":{"Unification":{"currentVault":{"count":3,"lastUpdated":1742348354718}}},"accommodate":{"accommodate":{"currentVault":{"count":5,"lastUpdated":1742997906196}}},"counterexample":{"counterexample":{"currentVault":{"count":3,"lastUpdated":1743522710682}}},"evaluate":{"evaluate":{"currentVault":{"count":2,"lastUpdated":1742344570417}}},"premises":{"premises":{"currentVault":{"count":3,"lastUpdated":1742958581022}}},"induction":{"induction":{"currentVault":{"count":13,"lastUpdated":1743898969953}}},"someone":{"someone":{"currentVault":{"count":10,"lastUpdated":1743039273382}}},"answer":{"answer":{"currentVault":{"count":33,"lastUpdated":1743531954732}}},"question":{"question":{"currentVault":{"count":22,"lastUpdated":1743535583861}}},"appealing":{"appealing":{"currentVault":{"count":2,"lastUpdated":1742955905800}}},"derivative":{"derivative":{"currentVault":{"count":28,"lastUpdated":1743536566560}}},"practice":{"practice":{"currentVault":{"count":23,"lastUpdated":1743119834762}}},"answering":{"answering":{"currentVault":{"count":6,"lastUpdated":1743038647589}}},"Concept":{"Concept":{"currentVault":{"count":5,"lastUpdated":1742440607824}}},"identify":{"identify":{"currentVault":{"count":13,"lastUpdated":1743535265964}}},"alternative":{"alternative":{"currentVault":{"count":6,"lastUpdated":1743461848379}}},"theoratical":{"theoratical":{"currentVault":{"count":4,"lastUpdated":1742614029184}}},"actually":{"actually":{"currentVault":{"count":10,"lastUpdated":1743017643711}}},"another":{"another":{"currentVault":{"count":3,"lastUpdated":1743520213359}}},"determine":{"determine":{"currentVault":{"count":10,"lastUpdated":1743386722163}}},"namely":{"namely":{"currentVault":{"count":3,"lastUpdated":1742996342827}}},"defining":{"defining":{"currentVault":{"count":2,"lastUpdated":1743037585520}}},"approach":{"approach":{"currentFile":{"count":4,"lastUpdated":1743011568500}}},"electricity":{"electricity":{"currentFile":{"count":8,"lastUpdated":1743009503907}}},"coherent":{"coherent":{"currentVault":{"count":4,"lastUpdated":1743536796090}}},"designating":{"designating":{"currentVault":{"count":2,"lastUpdated":1742333860060}}},"substructure":{"substructure":{"currentVault":{"count":5,"lastUpdated":1743013177216}}},"virtue":{"virtue":{"currentVault":{"count":5,"lastUpdated":1743443206817}}},"metaphysical":{"metaphysical":{"currentVault":{"count":18,"lastUpdated":1743524926738}}},"reject":{"reject":{"currentVault":{"count":1,"lastUpdated":1743011424722}}},"theoretical":{"theoretical":{"currentFile":{"count":7,"lastUpdated":1742342908678}}},"coherence":{"coherence":{"currentVault":{"count":2,"lastUpdated":1742596175698}}},"Epistemology":{"Epistemology":{"currentVault":{"count":3,"lastUpdated":1743212764223}}},"entities":{"entities":{"currentFile":{"count":31,"lastUpdated":1743536568362}}},"justifies":{"justifies":{"currentVault":{"count":7,"lastUpdated":1742610057225}}},"Design":{"Design":{"currentVault":{"count":4,"lastUpdated":1742344567672}}},"Everything":{"Everything":{"currentVault":{"count":5,"lastUpdated":1743536857906}}},"construction":{"construction":{"currentVault":{"count":5,"lastUpdated":1742437193709}}},"formulated":{"formulated":{"currentVault":{"count":5,"lastUpdated":1743520868753}}},"Because":{"Because":{"currentVault":{"count":5,"lastUpdated":1743017790016}}},"ontological":{"ontological":{"currentVault":{"count":10,"lastUpdated":1743560988859}}},"conceptual":{"conceptual":{"currentFile":{"count":6,"lastUpdated":1742342653812},"currentVault":{"count":2,"lastUpdated":1742959958957}}},"existence":{"existence":{"currentVault":{"count":18,"lastUpdated":1743470530903}}},"reflective":{"reflective":{"currentVault":{"count":6,"lastUpdated":1743609231714}}},"partial":{"partial":{"currentVault":{"count":3,"lastUpdated":1742956754549}}},"every":{"every":{"currentFile":{"count":12,"lastUpdated":1743890605308},"currentVault":{"count":4,"lastUpdated":1742598880516}}},"easily":{"easily":{"currentVault":{"count":5,"lastUpdated":1743013669745}}},"generate":{"generate":{"currentVault":{"count":12,"lastUpdated":1742949815423}}},"create":{"create":{"currentVault":{"count":2,"lastUpdated":1743211362717}}},"metaphysics":{"metaphysics":{"currentVault":{"count":1,"lastUpdated":1743008703246}}},"pluralism":{"pluralism":{"currentVault":{"count":3,"lastUpdated":1743211594872}}},"project":{"project":{"currentVault":{"count":11,"lastUpdated":1743040105894}}},"symbols":{"symbols":{"currentFile":{"count":32,"lastUpdated":1743388523416}}},"Every":{"Every":{"currentFile":{"count":3,"lastUpdated":1743466347464}}},"close":{"close":{"currentVault":{"count":4,"lastUpdated":1743017864655}}},"formulas":{"formulas":{"currentFile":{"count":27,"lastUpdated":1743388369159}}},"Prediction":{"Prediction":{"currentVault":{"count":2,"lastUpdated":1742435081597}}},"number":{"number":{"currentFile":{"count":6,"lastUpdated":1743033800698}}},"includes":{"includes":{"currentFile":{"count":2,"lastUpdated":1742996334995}}},"concatenating":{"concatenating":{"currentVault":{"count":1,"lastUpdated":1742999392746}}},"According":{"According":{"currentVault":{"count":3,"lastUpdated":1742957452026}}},"complicated":{"complicated":{"currentVault":{"count":5,"lastUpdated":1743030984690}}},"itself":{"itself":{"currentVault":{"count":8,"lastUpdated":1743536873643}}},"Suppose":{"Suppose":{"currentFile":{"count":9,"lastUpdated":1743389216860}}},"finite":{"finite":{"currentFile":{"count":5,"lastUpdated":1742247193219},"currentVault":{"count":1,"lastUpdated":1743202090574}}},"expression":{"expression":{"currentVault":{"count":6,"lastUpdated":1742340151915}}},"either":{"either":{"currentFile":{"count":2,"lastUpdated":1743387220972}}},"formulation":{"formulation":{"currentVault":{"count":5,"lastUpdated":1743898758334}}},"minimal":{"minimal":{"currentVault":{"count":1,"lastUpdated":1742599113992}}},"mention":{"mention":{"currentVault":{"count":2,"lastUpdated":1743025942785}}},"interpret":{"interpret":{"currentVault":{"count":9,"lastUpdated":1743033778574}}},"understood":{"understood":{"currentVault":{"count":8,"lastUpdated":1742954366654}}},"member":{"member":{"currentVault":{"count":11,"lastUpdated":1743560704525}}},"variable":{"variable":{"currentFile":{"count":32,"lastUpdated":1743388396965},"currentVault":{"count":1,"lastUpdated":1743917921912}}},"projecting":{"projecting":{"currentVault":{"count":5,"lastUpdated":1742435393902}}},"introduce":{"introduce":{"currentVault":{"count":5,"lastUpdated":1743031139118}}},"philosopher":{"philosopher":{"currentVault":{"count":4,"lastUpdated":1742604816258}}},"powerful":{"powerful":{"currentVault":{"count":2,"lastUpdated":1742342671043}}},"interesting":{"interesting":{"currentVault":{"count":2,"lastUpdated":1742960889380}}},"philosophic":{"philosophic":{"currentVault":{"count":2,"lastUpdated":1742945493456}}},"without":{"without":{"currentVault":{"count":7,"lastUpdated":1743037982027}}},"Chalmers":{"Chalmers":{"currentVault":{"count":2,"lastUpdated":1742337460650}}},"Metaphysics":{"Metaphysics":{"internalLink":{"count":9,"lastUpdated":1743523537173}}},"whether":{"whether":{"currentVault":{"count":7,"lastUpdated":1743119854298}}},"anything":{"anything":{"currentVault":{"count":4,"lastUpdated":1743890378413}}},"isolated":{"isolated":{"currentVault":{"count":2,"lastUpdated":1742614561179}}},"context-sensitive":{"context-sensitive":{"currentVault":{"count":6,"lastUpdated":1742953845219}}},"interpretation":{"interpretation":{"currentVault":{"count":1,"lastUpdated":1742598399022}}},"Linguistic":{"Linguistic":{"currentVault":{"count":2,"lastUpdated":1742940263034}}},"linguistic":{"linguistic":{"currentVault":{"count":13,"lastUpdated":1743119833077}}},"Corollary":{"Corollary":{"currentVault":{"count":3,"lastUpdated":1742252541033}}},"audience":{"audience":{"currentVault":{"count":4,"lastUpdated":1742952247557}}},"Causation":{"Causation":{"currentVault":{"count":3,"lastUpdated":1743216883458}}},"support":{"support":{"currentVault":{"count":7,"lastUpdated":1743463716773}}},"include":{"include":{"currentVault":{"count":9,"lastUpdated":1743536871908}}},"process":{"process":{"currentVault":{"count":2,"lastUpdated":1743898110357}}},"Second":{"Second":{"currentVault":{"count":6,"lastUpdated":1743040125831}}},"extend":{"extend":{"currentVault":{"count":2,"lastUpdated":1743466365248}}},"Reply":{"Reply":{"currentVault":{"count":6,"lastUpdated":1744776451428}}},"unhappy":{"unhappy":{"currentVault":{"count":1,"lastUpdated":1743898749286}}},"requirement":{"requirement":{"currentVault":{"count":7,"lastUpdated":1743520214866}}},"whole":{"whole":{"currentVault":{"count":4,"lastUpdated":1743037986925}}},"inconsistent":{"inconsistent":{"currentVault":{"count":20,"lastUpdated":1743894281886}}},"doubt":{"doubt":{"currentVault":{"count":2,"lastUpdated":1743116448086}}},"Virtue":{"Virtue":{"currentFile":{"count":3,"lastUpdated":1743442959308}}},"likely":{"likely":{"currentVault":{"count":1,"lastUpdated":1742944595320}}},"power":{"power":{"currentVault":{"count":3,"lastUpdated":1743026290474}}},"abstraction":{"abstraction":{"currentVault":{"count":8,"lastUpdated":1742334702106}}},"completeness":{"completeness":{"currentVault":{"count":3,"lastUpdated":1743367259689}}},"machenism":{"machenism":{"currentVault":{"count":3,"lastUpdated":1743012148463}}},"unexplained":{"unexplained":{"currentFile":{"count":7,"lastUpdated":1743522364095}}},"mostly":{"mostly":{"currentVault":{"count":2,"lastUpdated":1742340121550}}},"really":{"really":{"currentVault":{"count":3,"lastUpdated":1743470076886}}},"further":{"further":{"currentVault":{"count":4,"lastUpdated":1742958649738}}},"Natural":{"Natural":{"currentFile":{"count":2,"lastUpdated":1742610984691}}},"explainan":{"explainan":{"currentVault":{"count":4,"lastUpdated":1743039969952}}},"Distinction":{"Distinction":{"currentVault":{"count":4,"lastUpdated":1743559658715}}},"entity":{"entity":{"currentVault":{"count":13,"lastUpdated":1743536377877}}},"considering":{"considering":{"currentVault":{"count":2,"lastUpdated":1742611854979}}},"depend":{"depend":{"currentVault":{"count":5,"lastUpdated":1742950114624}}},"repeat":{"repeat":{"currentVault":{"count":2,"lastUpdated":1742955495411}}},"independent":{"independent":{"currentVault":{"count":4,"lastUpdated":1742614691849}}},"Ultimately":{"Ultimately":{"currentVault":{"count":4,"lastUpdated":1742950294552}}},"affairs":{"affairs":{"currentVault":{"count":6,"lastUpdated":1743025648317}}},"second":{"second":{"currentVault":{"count":14,"lastUpdated":1742945531641}}},"order":{"order":{"currentVault":{"count":2,"lastUpdated":1742440666180}}},"presuppose":{"presuppose":{"currentVault":{"count":9,"lastUpdated":1743011756477}}},"Consider":{"Consider":{"currentVault":{"count":6,"lastUpdated":1743200034336}}},"sentence":{"sentence":{"currentFile":{"count":25,"lastUpdated":1742247069384}}},"naturally":{"naturally":{"currentVault":{"count":3,"lastUpdated":1742342667278}}},"mathematically":{"mathematically":{"currentVault":{"count":2,"lastUpdated":1742429910143}}},"entail":{"entail":{"currentVault":{"count":2,"lastUpdated":1742948208230}}},"satisfiable":{"satisfiable":{"currentFile":{"count":4,"lastUpdated":1743033332799}}},"unsatisfiable":{"unsatisfiable":{"currentVault":{"count":1,"lastUpdated":1743909090613}}},"closure":{"closure":{"currentVault":{"count":1,"lastUpdated":1743031254408}}},"problematic":{"problematic":{"currentVault":{"count":7,"lastUpdated":1743559070183}}},"primitive":{"primitive":{"currentVault":{"count":4,"lastUpdated":1743207326078}}},"matter":{"matter":{"currentVault":{"count":4,"lastUpdated":1742666720182}}},"investigation":{"investigation":{"currentVault":{"count":2,"lastUpdated":1742944568450}}},"analogous":{"analogous":{"currentVault":{"count":7,"lastUpdated":1743012126410}}},"involve":{"involve":{"currentVault":{"count":4,"lastUpdated":1743204908707}}},"movement":{"movement":{"currentVault":{"count":9,"lastUpdated":1743009429970}}},"instead":{"instead":{"currentFile":{"count":2,"lastUpdated":1742949709627}}},"behavior":{"behavior":{"currentVault":{"count":9,"lastUpdated":1743123449379}}},"available":{"available":{"currentVault":{"count":6,"lastUpdated":1742702773365}}},"composition":{"composition":{"currentVault":{"count":2,"lastUpdated":1742337487006}}},"physically":{"physically":{"currentVault":{"count":2,"lastUpdated":1742342839378}}},"Assumption":{"Assumption":{"currentVault":{"count":5,"lastUpdated":1743894303034}}},"condition":{"condition":{"currentVault":{"count":13,"lastUpdated":1743117225584}}},"previous":{"previous":{"currentVault":{"count":2,"lastUpdated":1742960000281}}},"backwards":{"backwards":{"currentVault":{"count":4,"lastUpdated":1742614021322}}},"explicitly":{"explicitly":{"currentVault":{"count":2,"lastUpdated":1743014349974}}},"charity":{"charity":{"currentVault":{"count":2,"lastUpdated":1743014439431}}},"instance":{"instance":{"currentVault":{"count":20,"lastUpdated":1743518181564}}},"probably":{"probably":{"currentVault":{"count":7,"lastUpdated":1743561397058}}},"suggest":{"suggest":{"currentVault":{"count":4,"lastUpdated":1743119393405}}},"paper":{"paper":{"currentFile":{"count":3,"lastUpdated":1743039947904}}},"reconstruct":{"reconstruct":{"currentVault":{"count":3,"lastUpdated":1743014387660}}},"capture":{"capture":{"currentVault":{"count":2,"lastUpdated":1742955789935}}},"surely":{"surely":{"currentVault":{"count":3,"lastUpdated":1743000413340}}},"circular":{"circular":{"currentVault":{"count":3,"lastUpdated":1743033178096}}},"exclude":{"exclude":{"currentVault":{"count":6,"lastUpdated":1743033264521}}},"provide":{"provide":{"currentVault":{"count":4,"lastUpdated":1743535189043}}},"unclear":{"unclear":{"currentVault":{"count":2,"lastUpdated":1743119365251}}},"intuition":{"intuition":{"currentFile":{"count":10,"lastUpdated":1743033058533}}},"argue":{"argue":{"currentVault":{"count":1,"lastUpdated":1743117210354}}},"grammatical":{"grammatical":{"currentVault":{"count":2,"lastUpdated":1743535237873}}},"address":{"address":{"currentVault":{"count":3,"lastUpdated":1743040242289}}},"misunderstanding":{"misunderstanding":{"currentVault":{"count":2,"lastUpdated":1743015251171}}},"external":{"external":{"currentVault":{"count":4,"lastUpdated":1742344625619}}},"undertsand":{"undertsand":{"currentVault":{"count":2,"lastUpdated":1742438119855}}},"consider":{"consider":{"currentFile":{"count":3,"lastUpdated":1743217704916}}},"discuss":{"discuss":{"currentVault":{"count":3,"lastUpdated":1743037268751}}},"Compactness":{"Compactness":{"currentFile":{"count":1,"lastUpdated":1742247174884}}},"subset":{"subset":{"currentFile":{"count":2,"lastUpdated":1742247229347},"currentVault":{"count":6,"lastUpdated":1743010146029}}},"Soundness":{"Soundness":{"currentFile":{"count":1,"lastUpdated":1742251550937}}},"derivable":{"derivable":{"currentFile":{"count":1,"lastUpdated":1742251560483}}},"undischarged":{"undischarged":{"currentFile":{"count":1,"lastUpdated":1742251569659}}},"concept":{"concept":{"currentVault":{"count":24,"lastUpdated":1743014298973}}},"engineer":{"engineer":{"currentVault":{"count":5,"lastUpdated":1742959901831}}},"Conceptual":{"Conceptual":{"currentFile":{"count":7,"lastUpdated":1742342966399}}},"Engineer":{"Engineer":{"currentVault":{"count":5,"lastUpdated":1742342978664}}},"implements":{"implements":{"currentVault":{"count":2,"lastUpdated":1742341531078}}},"Given":{"Given":{"currentVault":{"count":1,"lastUpdated":1742333894002}}},"paradigm":{"paradigm":{"currentVault":{"count":1,"lastUpdated":1742333945849}}},"Implements":{"Implements":{"currentVault":{"count":1,"lastUpdated":1742333962517}}},"Implementation":{"Implementation":{"currentVault":{"count":2,"lastUpdated":1742344592400}}},"Actually":{"Actually":{"currentVault":{"count":2,"lastUpdated":1743038063314}}},"Evaluation":{"Evaluation":{"currentVault":{"count":1,"lastUpdated":1742334142022}}},"purpose":{"purpose":{"currentVault":{"count":1,"lastUpdated":1742334365172}}},"software":{"software":{"currentVault":{"count":3,"lastUpdated":1742334915874}}},"engineering":{"engineering":{"currentFile":{"count":9,"lastUpdated":1742344054495},"currentVault":{"count":2,"lastUpdated":1742961091586}}},"bridge":{"bridge":{"currentVault":{"count":2,"lastUpdated":1742334913357}}},"Fixing":{"Fixing":{"currentVault":{"count":1,"lastUpdated":1742334903080}}},"consciousness":{"consciousness":{"currentVault":{"count":1,"lastUpdated":1742335830236}}},"injustice":{"injustice":{"currentVault":{"count":1,"lastUpdated":1742335902959}}},"compositionality":{"compositionality":{"currentVault":{"count":1,"lastUpdated":1742337488604}}},"e-belief":{"e-belief":{"currentFile":{"count":2,"lastUpdated":1742338856582}}},"associate":{"associate":{"currentVault":{"count":1,"lastUpdated":1742338848401}}},"Homonymous":{"Homonymous":{"currentFile":{"count":1,"lastUpdated":1742340103220}}},"re-engineering":{"re-engineering":{"currentFile":{"count":1,"lastUpdated":1742340126017}}},"Heteronomous":{"Heteronomous":{"currentFile":{"count":1,"lastUpdated":1742340164367}}},"challenge":{"challenge":{"currentVault":{"count":1,"lastUpdated":1742340295785}}},"explication":{"explication":{"currentFile":{"count":1,"lastUpdated":1742340307082}}},"standpoint":{"standpoint":{"currentVault":{"count":1,"lastUpdated":1742340635283}}},"homonymous":{"homonymous":{"currentFile":{"count":1,"lastUpdated":1742341309747}}},"married":{"married":{"currentVault":{"count":1,"lastUpdated":1742341385298}}},"Theoratical":{"Theoratical":{"currentVault":{"count":1,"lastUpdated":1742341503465}}},"confusion":{"confusion":{"currentVault":{"count":1,"lastUpdated":1742341517892}}},"Import":{"Import":{"currentVault":{"count":2,"lastUpdated":1742439877170}}},"practically":{"practically":{"currentVault":{"count":2,"lastUpdated":1742342879305}}},"achieving":{"achieving":{"currentVault":{"count":1,"lastUpdated":1742342597450}}},"Theoretically":{"Theoretically":{"currentFile":{"count":1,"lastUpdated":1742342638032}}},"Thesis":{"Thesis":{"currentFile":{"count":1,"lastUpdated":1742342752795}}},"potential":{"potential":{"currentVault":{"count":1,"lastUpdated":1742342783971}}},"Physicalism":{"Physicalism":{"currentVault":{"count":1,"lastUpdated":1742342808746}}},"ground":{"ground":{"currentVault":{"count":6,"lastUpdated":1743523231783}}},"grounding":{"grounding":{"currentFile":{"count":17,"lastUpdated":1743536860766}}},"physicalism":{"physicalism":{"currentVault":{"count":1,"lastUpdated":1742342840829}}},"Pluralism":{"Pluralism":{"currentFile":{"count":1,"lastUpdated":1742343899783},"currentVault":{"count":1,"lastUpdated":1743210576004}}},"difficult":{"difficult":{"currentVault":{"count":2,"lastUpdated":1742430005437}}},"Difficult":{"Difficult":{"currentVault":{"count":1,"lastUpdated":1742344606706}}},"Challenge":{"Challenge":{"currentFile":{"count":2,"lastUpdated":1742344667024}}},"trump":{"trump":{"currentVault":{"count":1,"lastUpdated":1742429838828}}},"Universe":{"Universe":{"currentVault":{"count":1,"lastUpdated":1742429927281}}},"hierarchy":{"hierarchy":{"currentVault":{"count":2,"lastUpdated":1743561027690}}},"Involve":{"Involve":{"currentVault":{"count":1,"lastUpdated":1742430095015}}},"non-causal":{"non-causal":{"currentFile":{"count":1,"lastUpdated":1742430098908}}},"intuitive":{"intuitive":{"currentVault":{"count":2,"lastUpdated":1743039776008}}},"Entity":{"Entity":{"currentVault":{"count":1,"lastUpdated":1742431639176}}},"Ground":{"Ground":{"currentVault":{"count":1,"lastUpdated":1742431641604}}},"Propositional":{"Propositional":{"currentFile":{"count":1,"lastUpdated":1742433226315}}},"grounded":{"grounded":{"currentFile":{"count":1,"lastUpdated":1742433267209}}},"Upside":{"Upside":{"currentVault":{"count":1,"lastUpdated":1742433439160}}},"Dispute":{"Dispute":{"currentVault":{"count":1,"lastUpdated":1742435057161}}},"Connect":{"Connect":{"currentVault":{"count":1,"lastUpdated":1742435069335}}},"sentential":{"sentential":{"currentFile":{"count":1,"lastUpdated":1742435114208}}},"Separate":{"Separate":{"currentVault":{"count":1,"lastUpdated":1742435939631}}},"identical":{"identical":{"currentVault":{"count":1,"lastUpdated":1742436001311}}},"irreflexive":{"irreflexive":{"currentVault":{"count":2,"lastUpdated":1742604570708}}},"Separation":{"Separation":{"currentVault":{"count":1,"lastUpdated":1742437028652}}},"Further":{"Further":{"currentVault":{"count":1,"lastUpdated":1742439873551}}},"Absolute":{"Absolute":{"currentVault":{"count":2,"lastUpdated":1742597364359}}},"small":{"small":{"currentVault":{"count":1,"lastUpdated":1742441473187}}},"unique":{"unique":{"currentVault":{"count":1,"lastUpdated":1742441576128}}},"Thomasson":{"Thomasson":{"currentVault":{"count":1,"lastUpdated":1742441716949}}},"overarching":{"overarching":{"currentFile":{"count":1,"lastUpdated":1742595056291}}},"relativized":{"relativized":{"currentVault":{"count":1,"lastUpdated":1742595104343}}},"partially":{"partially":{"currentVault":{"count":5,"lastUpdated":1743220592686}}},"Socrates":{"Socrates":{"currentVault":{"count":8,"lastUpdated":1743535314104}}},"parallel":{"parallel":{"currentVault":{"count":1,"lastUpdated":1742596092524}}},"fundamentalism":{"fundamentalism":{"currentVault":{"count":4,"lastUpdated":1743461845427}}},"fundamentally":{"fundamentally":{"currentFile":{"count":1,"lastUpdated":1742596906251}}},"absoute":{"absoute":{"currentVault":{"count":1,"lastUpdated":1742596922157}}},"absolute":{"absolute":{"currentFile":{"count":4,"lastUpdated":1742601657832}}},"Independence":{"Independence":{"currentVault":{"count":5,"lastUpdated":1742614493602}}},"Completeness":{"Completeness":{"currentVault":{"count":4,"lastUpdated":1743386586385}}},"eliminate":{"eliminate":{"currentVault":{"count":1,"lastUpdated":1742600112784}}},"Indispensability":{"Indispensability":{"currentVault":{"count":2,"lastUpdated":1742601330475}}},"Unexplained":{"Unexplained":{"currentVault":{"count":1,"lastUpdated":1742601104315}}},"independence":{"independence":{"currentFile":{"count":2,"lastUpdated":1742614577858}}},"weighting":{"weighting":{"currentVault":{"count":1,"lastUpdated":1742601349932}}},"History":{"History":{"currentVault":{"count":1,"lastUpdated":1742603676840}}},"Reality":{"Reality":{"currentFile":{"count":1,"lastUpdated":1742603785294}}},"Historically":{"Historically":{"currentVault":{"count":1,"lastUpdated":1742604803504}}},"comtemporary":{"comtemporary":{"currentVault":{"count":1,"lastUpdated":1742604813704}}},"indirect":{"indirect":{"currentVault":{"count":1,"lastUpdated":1742605268509}}},"history":{"history":{"currentFile":{"count":1,"lastUpdated":1742608082862}}},"Ultimate":{"Ultimate":{"currentFile":{"count":7,"lastUpdated":1743210219110}}},"target":{"target":{"currentVault":{"count":4,"lastUpdated":1743535650072}}},"beliefs":{"beliefs":{"currentVault":{"count":2,"lastUpdated":1742610038597}}},"ultimate":{"ultimate":{"currentFile":{"count":14,"lastUpdated":1743561414854}}},"typical":{"typical":{"currentVault":{"count":2,"lastUpdated":1742962205732}}},"Explain":{"Explain":{"currentFile":{"count":2,"lastUpdated":1742614633117}}},"general":{"general":{"currentFile":{"count":1,"lastUpdated":1742610539768}}},"non-arbitrary":{"non-arbitrary":{"currentFile":{"count":3,"lastUpdated":1743561421746}}},"stopped":{"stopped":{"currentVault":{"count":1,"lastUpdated":1742611067276}}},"explanandum":{"explanandum":{"currentVault":{"count":8,"lastUpdated":1743220590042}}},"self-explanatory":{"self-explanatory":{"currentFile":{"count":1,"lastUpdated":1742612212696}}},"stopping":{"stopping":{"currentFile":{"count":2,"lastUpdated":1743212740411}}},"justified":{"justified":{"currentFile":{"count":2,"lastUpdated":1742614201545}}},"causal":{"causal":{"currentFile":{"count":6,"lastUpdated":1743039708071}}},"hylomorphic":{"hylomorphic":{"currentVault":{"count":1,"lastUpdated":1742666239467}}},"Flesh":{"Flesh":{"currentFile":{"count":1,"lastUpdated":1742666315071}}},"Molecule":{"Molecule":{"currentVault":{"count":1,"lastUpdated":1742666327203}}},"Biological":{"Biological":{"currentVault":{"count":2,"lastUpdated":1742666451448}}},"accident":{"accident":{"currentVault":{"count":5,"lastUpdated":1742666794629}}},"fleshhood":{"fleshhood":{"currentFile":{"count":1,"lastUpdated":1742666438398}}},"Lever":{"Lever":{"currentFile":{"count":1,"lastUpdated":1742666577622}}},"Prime":{"Prime":{"currentVault":{"count":1,"lastUpdated":1742666586364}}},"biological":{"biological":{"currentFile":{"count":1,"lastUpdated":1742666595814}}},"matterhood":{"matterhood":{"currentFile":{"count":1,"lastUpdated":1742666600451}}},"cellhood":{"cellhood":{"currentFile":{"count":1,"lastUpdated":1742666799181}}},"prime":{"prime":{"currentFile":{"count":2,"lastUpdated":1742667135180}}},"opposite":{"opposite":{"currentVault":{"count":1,"lastUpdated":1742667156256}}},"opposition":{"opposition":{"currentVault":{"count":1,"lastUpdated":1742667157790}}},"infinity":{"infinity":{"currentVault":{"count":1,"lastUpdated":1742667161478}}},"Probe":{"Probe":{"currentVault":{"count":3,"lastUpdated":1743216985684}}},"\\UnaryInfC{$":{"\\UnaryInfC{$":{"currentFile":{"count":1,"lastUpdated":1742695563907}}},"\\usepackage{}":{"\\usepackage{}":{"currentFile":{"count":1,"lastUpdated":1742740363955}}},"preference":{"preference":{"currentVault":{"count":3,"lastUpdated":1743039958807}}},"reflect":{"reflect":{"currentVault":{"count":1,"lastUpdated":1742942942030}}},"tentative":{"tentative":{"currentVault":{"count":1,"lastUpdated":1742944708135}}},"criterion":{"criterion":{"currentVault":{"count":4,"lastUpdated":1742950429127}}},"might":{"might":{"currentVault":{"count":1,"lastUpdated":1742945128537}}},"verify":{"verify":{"currentFile":{"count":1,"lastUpdated":1742946237996}}},"ancient":{"ancient":{"currentVault":{"count":1,"lastUpdated":1742946922583}}},"paradox":{"paradox":{"currentFile":{"count":1,"lastUpdated":1742947782277}}},"haven":{"haven":{"currentVault":{"count":1,"lastUpdated":1742947788271}}},"literature":{"literature":{"currentVault":{"count":1,"lastUpdated":1742947809156}}},"baptism":{"baptism":{"currentVault":{"count":1,"lastUpdated":1742947952134}}},"instances":{"instances":{"currentFile":{"count":3,"lastUpdated":1742950655180}}},"agreed":{"agreed":{"currentVault":{"count":1,"lastUpdated":1742948144507}}},"community":{"community":{"currentVault":{"count":2,"lastUpdated":1743119794621}}},"inquire":{"inquire":{"currentVault":{"count":2,"lastUpdated":1743039966469}}},"ambiguous":{"ambiguous":{"currentVault":{"count":1,"lastUpdated":1742949390048}}},"theorizing":{"theorizing":{"currentVault":{"count":2,"lastUpdated":1743039985214}}},"However":{"However":{"currentFile":{"count":3,"lastUpdated":1743026319515}}},"slightly":{"slightly":{"currentVault":{"count":1,"lastUpdated":1742950548339}}},"formalized":{"formalized":{"currentVault":{"count":1,"lastUpdated":1742950552488}}},"ultimately":{"ultimately":{"currentVault":{"count":1,"lastUpdated":1742950648539}}},"depiction":{"depiction":{"currentVault":{"count":1,"lastUpdated":1742951003936}}},"presupposition":{"presupposition":{"currentVault":{"count":1,"lastUpdated":1742952429151}}},"Context-sensitivity":{"Context-sensitivity":{"currentVault":{"count":1,"lastUpdated":1742952639928}}},"appropriateness":{"appropriateness":{"currentVault":{"count":1,"lastUpdated":1742952647991}}},"sensitive":{"sensitive":{"currentVault":{"count":1,"lastUpdated":1742953439738}}},"factor":{"factor":{"currentVault":{"count":2,"lastUpdated":1742954512754}}},"conjunctive":{"conjunctive":{"currentVault":{"count":2,"lastUpdated":1742954648524}}},"incredibly":{"incredibly":{"currentVault":{"count":1,"lastUpdated":1742954359978}}},"snake":{"snake":{"currentFile":{"count":1,"lastUpdated":1742955091859}}},"asked":{"asked":{"currentVault":{"count":1,"lastUpdated":1742955095136}}},"conversation":{"conversation":{"currentVault":{"count":1,"lastUpdated":1742955366153}}},"longer":{"longer":{"currentVault":{"count":1,"lastUpdated":1742955635048}}},"mereological":{"mereological":{"currentVault":{"count":6,"lastUpdated":1744775771542}}},"conjuncts":{"conjuncts":{"currentVault":{"count":2,"lastUpdated":1743528833484}}},"euthyphro":{"euthyphro":{"currentVault":{"count":1,"lastUpdated":1742957394406}}},"delimma":{"delimma":{"currentVault":{"count":4,"lastUpdated":1743033131506}}},"maintain":{"maintain":{"currentVault":{"count":2,"lastUpdated":1743036609301}}},"Intuitive":{"Intuitive":{"currentVault":{"count":2,"lastUpdated":1742999505709}}},"erosion":{"erosion":{"currentVault":{"count":1,"lastUpdated":1742958505017}}},"satisfied":{"satisfied":{"currentVault":{"count":2,"lastUpdated":1742959659824}}},"Minimal":{"Minimal":{"currentVault":{"count":1,"lastUpdated":1742958921194}}},"Railton":{"Railton":{"currentFile":{"count":22,"lastUpdated":1743040257980}}},"align":{"align":{"currentVault":{"count":1,"lastUpdated":1742959997413}}},"railton":{"railton":{"currentFile":{"count":1,"lastUpdated":1742960900531}}},"naming":{"naming":{"currentFile":{"count":1,"lastUpdated":1742961912933}}},"mechanical":{"mechanical":{"currentVault":{"count":2,"lastUpdated":1743008809295}}},"Mechanism":{"Mechanism":{"currentVault":{"count":1,"lastUpdated":1742962215051}}},"Explaining":{"Explaining":{"currentVault":{"count":1,"lastUpdated":1742962235207}}},"Anyway":{"Anyway":{"currentVault":{"count":1,"lastUpdated":1742996353902}}},"Surely":{"Surely":{"currentVault":{"count":3,"lastUpdated":1743000650446}}},"Obvious":{"Obvious":{"currentVault":{"count":1,"lastUpdated":1742996860544}}},"probabilistic":{"probabilistic":{"currentVault":{"count":1,"lastUpdated":1742998017496}}},"deterministic":{"deterministic":{"currentVault":{"count":1,"lastUpdated":1742998031118}}},"addition":{"addition":{"currentVault":{"count":1,"lastUpdated":1742998092660}}},"violate":{"violate":{"currentVault":{"count":4,"lastUpdated":1743471477929}}},"choose":{"choose":{"currentFile":{"count":1,"lastUpdated":1742998489851}}},"admit":{"admit":{"currentFile":{"count":1,"lastUpdated":1742998502348}}},"chooses":{"chooses":{"currentFile":{"count":1,"lastUpdated":1742998533684}}},"adopt":{"adopt":{"currentFile":{"count":1,"lastUpdated":1742998576760}}},"internet":{"internet":{"currentVault":{"count":1,"lastUpdated":1742998859892}}},"analogy":{"analogy":{"currentFile":{"count":7,"lastUpdated":1743012133553}}},"resist":{"resist":{"currentVault":{"count":3,"lastUpdated":1743011334651}}},"talking":{"talking":{"currentVault":{"count":2,"lastUpdated":1743008803915}}},"metalinguistic":{"metalinguistic":{"currentVault":{"count":13,"lastUpdated":1743038118364}}},"justify":{"justify":{"currentVault":{"count":4,"lastUpdated":1743438930446}}},"worldly":{"worldly":{"currentVault":{"count":2,"lastUpdated":1743037098945}}},"absurd":{"absurd":{"currentVault":{"count":1,"lastUpdated":1743000063248}}},"Maybe":{"Maybe":{"currentVault":{"count":2,"lastUpdated":1743219934234}}},"strategy":{"strategy":{"currentVault":{"count":2,"lastUpdated":1743008812376}}},"metalanguage":{"metalanguage":{"currentFile":{"count":2,"lastUpdated":1743037275670}}},"biology":{"biology":{"currentVault":{"count":2,"lastUpdated":1743017682707}}},"inevitable":{"inevitable":{"currentVault":{"count":1,"lastUpdated":1743008476066}}},"attention":{"attention":{"currentVault":{"count":1,"lastUpdated":1743008694309}}},"molecule":{"molecule":{"currentVault":{"count":1,"lastUpdated":1743008771019}}},"electrons":{"electrons":{"currentVault":{"count":2,"lastUpdated":1743008829053}}},"structural":{"structural":{"currentVault":{"count":1,"lastUpdated":1743009053592}}},"regarding":{"regarding":{"currentVault":{"count":1,"lastUpdated":1743009425784}}},"dismiss":{"dismiss":{"currentVault":{"count":1,"lastUpdated":1743011484810}}},"discourse":{"discourse":{"currentVault":{"count":1,"lastUpdated":1743011630976}}},"explicit":{"explicit":{"currentVault":{"count":1,"lastUpdated":1743014280432}}},"official":{"official":{"currentVault":{"count":1,"lastUpdated":1743014512095}}},"state":{"state":{"currentFile":{"count":1,"lastUpdated":1743017637000}}},"Euthyphro":{"Euthyphro":{"currentFile":{"count":3,"lastUpdated":1743033129761}}},"Eventual":{"Eventual":{"currentVault":{"count":1,"lastUpdated":1743025201563}}},"Eventually":{"Eventually":{"currentVault":{"count":1,"lastUpdated":1743025202840}}},"causally":{"causally":{"currentVault":{"count":3,"lastUpdated":1743520806049}}},"earlier":{"earlier":{"currentFile":{"count":1,"lastUpdated":1743025957181}}},"reconsider":{"reconsider":{"currentVault":{"count":1,"lastUpdated":1743026966291}}},"About":{"About":{"internalLink":{"count":1,"lastUpdated":1743027455311}}},"appeal":{"appeal":{"currentFile":{"count":1,"lastUpdated":1743027896313}}},"relationship":{"relationship":{"currentVault":{"count":1,"lastUpdated":1743028145508}}},"embark":{"embark":{"currentVault":{"count":1,"lastUpdated":1743028637408}}},"radically":{"radically":{"currentVault":{"count":2,"lastUpdated":1743119980310}}},"binary":{"binary":{"currentVault":{"count":1,"lastUpdated":1743029449564}}},"express":{"express":{"currentVault":{"count":2,"lastUpdated":1743029967036}}},"After":{"After":{"currentFile":{"count":1,"lastUpdated":1743031023923}}},"prompt":{"prompt":{"currentVault":{"count":1,"lastUpdated":1743031032777}}},"original":{"original":{"currentVault":{"count":1,"lastUpdated":1743033291874}}},"natural":{"natural":{"currentFile":{"count":1,"lastUpdated":1743033799328}}},"upshot":{"upshot":{"currentVault":{"count":1,"lastUpdated":1743034455154}}},"ensure":{"ensure":{"currentVault":{"count":1,"lastUpdated":1743034664195}}},"Introduce":{"Introduce":{"currentFile":{"count":1,"lastUpdated":1743036900668}}},"thorough":{"thorough":{"currentVault":{"count":1,"lastUpdated":1743037264594}}},"destroying":{"destroying":{"currentVault":{"count":1,"lastUpdated":1743037984482}}},"remain":{"remain":{"currentVault":{"count":1,"lastUpdated":1743038662563}}},"bullet":{"bullet":{"currentVault":{"count":1,"lastUpdated":1743039184012}}},"aiming":{"aiming":{"currentVault":{"count":1,"lastUpdated":1743040146355}}},"Final":{"Final":{"currentVault":{"count":1,"lastUpdated":1743040224972}}},"follow":{"follow":{"currentVault":{"count":3,"lastUpdated":1743907505187}}},"impossibility":{"impossibility":{"currentVault":{"count":1,"lastUpdated":1743115466033}}},"comparison":{"comparison":{"currentVault":{"count":4,"lastUpdated":1743119274678}}},"ashamed":{"ashamed":{"currentFile":{"count":7,"lastUpdated":1743119602700}}},"compare":{"compare":{"currentVault":{"count":2,"lastUpdated":1743115842686}}},"certain":{"certain":{"currentVault":{"count":5,"lastUpdated":1743117430986}}},"selves":{"selves":{"currentFile":{"count":2,"lastUpdated":1743123432141}}},"comparing":{"comparing":{"currentVault":{"count":1,"lastUpdated":1743115861134}}},"contradictory":{"contradictory":{"currentVault":{"count":1,"lastUpdated":1743116409651}}},"remark":{"remark":{"currentVault":{"count":1,"lastUpdated":1743117414153}}},"factive":{"factive":{"currentVault":{"count":1,"lastUpdated":1743117423432}}},"solipsist":{"solipsist":{"currentFile":{"count":3,"lastUpdated":1743119987061}}},"expectation":{"expectation":{"currentVault":{"count":3,"lastUpdated":1743119691775}}},"disappointed":{"disappointed":{"currentVault":{"count":2,"lastUpdated":1743119345549}}},"ourselves":{"ourselves":{"currentVault":{"count":1,"lastUpdated":1743119285801}}},"disappointment":{"disappointment":{"currentVault":{"count":2,"lastUpdated":1743119369494}}},"shame":{"shame":{"currentFile":{"count":2,"lastUpdated":1743119873055}}},"mountain":{"mountain":{"currentVault":{"count":2,"lastUpdated":1743119456249}}},"expect":{"expect":{"currentVault":{"count":1,"lastUpdated":1743119450702}}},"should":{"should":{"currentFile":{"count":1,"lastUpdated":1743119856402}}},"emotion":{"emotion":{"currentVault":{"count":1,"lastUpdated":1743119860217}}},"fine-grained":{"fine-grained":{"currentVault":{"count":1,"lastUpdated":1743123462187}}},"contingent":{"contingent":{"currentVault":{"count":1,"lastUpdated":1743200585111}}},"Heidegger":{"Heidegger":{"currentVault":{"count":1,"lastUpdated":1743201144209}}},"Well-foundedness":{"Well-foundedness":{"currentFile":{"count":1,"lastUpdated":1743202197347}}},"well-foundedness":{"well-foundedness":{"currentFile":{"count":1,"lastUpdated":1743202206319}}},"descendant":{"descendant":{"currentVault":{"count":1,"lastUpdated":1743202230086}}},"Purity":{"Purity":{"currentVault":{"count":2,"lastUpdated":1743204894744}}},"Fundamental":{"Fundamental":{"currentFile":{"count":5,"lastUpdated":1743459690755}}},"constituent":{"constituent":{"currentVault":{"count":1,"lastUpdated":1743204923154}}},"purity":{"purity":{"currentFile":{"count":1,"lastUpdated":1743206557692}}},"lunch":{"lunch":{"currentFile":{"count":1,"lastUpdated":1743207199311}}},"innocent":{"innocent":{"currentVault":{"count":1,"lastUpdated":1743209768848}}},"Acceptance":{"Acceptance":{"currentVault":{"count":1,"lastUpdated":1743210208692}}},"Priority":{"Priority":{"currentVault":{"count":2,"lastUpdated":1743210979727}}},"Monism":{"Monism":{"currentVault":{"count":1,"lastUpdated":1743210982409}}},"direct":{"direct":{"currentVault":{"count":1,"lastUpdated":1743211227605}}},"Essence":{"Essence":{"currentVault":{"count":2,"lastUpdated":1743211772809}}},"middle":{"middle":{"currentFile":{"count":1,"lastUpdated":1743211791818}}},"bachelor":{"bachelor":{"currentVault":{"count":1,"lastUpdated":1743212277564}}},"unmarried":{"unmarried":{"currentVault":{"count":1,"lastUpdated":1743212285990}}},"Substance":{"Substance":{"currentFile":{"count":1,"lastUpdated":1743212302295}}},"Substantive":{"Substantive":{"currentFile":{"count":1,"lastUpdated":1743212303736}}},"Autonomy":{"Autonomy":{"currentVault":{"count":2,"lastUpdated":1743212309501}}},"Autonomous":{"Autonomous":{"currentFile":{"count":1,"lastUpdated":1743212310874}}},"essence":{"essence":{"currentVault":{"count":1,"lastUpdated":1743212598276}}},"autonomous":{"autonomous":{"currentFile":{"count":2,"lastUpdated":1743472296004}}},"Regress":{"Regress":{"currentVault":{"count":1,"lastUpdated":1743212773026}}},"bottom":{"bottom":{"currentFile":{"count":1,"lastUpdated":1743217064377}}},"begging":{"begging":{"currentVault":{"count":2,"lastUpdated":1743525930547}}},"regression":{"regression":{"currentVault":{"count":6,"lastUpdated":1743531948349}}},"inadequate":{"inadequate":{"currentVault":{"count":1,"lastUpdated":1743219979259}}},"non-fundamental":{"non-fundamental":{"currentFile":{"count":6,"lastUpdated":1743523221797}}},"Finish":{"Finish":{"currentVault":{"count":1,"lastUpdated":1743367333765}}},"obtain":{"obtain":{"currentVault":{"count":1,"lastUpdated":1743387323545}}},"countably":{"countably":{"currentFile":{"count":1,"lastUpdated":1743387333902}}},"Saturated":{"Saturated":{"currentVault":{"count":1,"lastUpdated":1743387521888}}},"saturated":{"saturated":{"currentFile":{"count":3,"lastUpdated":1743389256904}}},"enumeration":{"enumeration":{"currentFile":{"count":1,"lastUpdated":1743388341875}}},"regress":{"regress":{"currentFile":{"count":4,"lastUpdated":1743559038312}}},"entire":{"entire":{"currentVault":{"count":1,"lastUpdated":1743391632151}}},"Response":{"Response":{"currentVault":{"count":1,"lastUpdated":1743392694420}}},"whatsoever":{"whatsoever":{"currentVault":{"count":4,"lastUpdated":1743532520102}}},"flamingo":{"flamingo":{"currentFile":{"count":1,"lastUpdated":1743442731333}}},"Theoretical":{"Theoretical":{"currentFile":{"count":2,"lastUpdated":1743443205085}}},"Unified":{"Unified":{"currentVault":{"count":1,"lastUpdated":1743443259256}}},"unified":{"unified":{"currentVault":{"count":2,"lastUpdated":1743458087552}}},"separate":{"separate":{"currentVault":{"count":1,"lastUpdated":1743443376874}}},"unifies":{"unifies":{"currentVault":{"count":1,"lastUpdated":1743443843784}}},"plurality":{"plurality":{"currentVault":{"count":1,"lastUpdated":1743444245843}}},"Infinitist":{"Infinitist":{"currentFile":{"count":2,"lastUpdated":1743523543423}}},"category":{"category":{"currentVault":{"count":1,"lastUpdated":1743459594785}}},"infinitist":{"infinitist":{"currentFile":{"count":4,"lastUpdated":1743559044886}}},"generality":{"generality":{"currentFile":{"count":2,"lastUpdated":1743526343504}}},"Trouble":{"Trouble":{"currentVault":{"count":1,"lastUpdated":1743461854895}}},"tradition":{"tradition":{"currentVault":{"count":1,"lastUpdated":1743461951370}}},"Lindenbaum":{"Lindenbaum":{"currentFile":{"count":1,"lastUpdated":1743466339492}}},"suppose":{"suppose":{"currentFile":{"count":1,"lastUpdated":1743469272967}}},"invokes":{"invokes":{"currentVault":{"count":1,"lastUpdated":1743469290969}}},"Schaffer":{"Schaffer":{"currentFile":{"count":2,"lastUpdated":1743472256575}}},"Infinite":{"Infinite":{"currentFile":{"count":1,"lastUpdated":1743470064203}}},"never":{"never":{"currentFile":{"count":2,"lastUpdated":1743528778124}}},"Dasgupta":{"Dasgupta":{"currentFile":{"count":2,"lastUpdated":1743472285846}}},"Target":{"Target":{"currentFile":{"count":1,"lastUpdated":1743470661425}}},"schaffer":{"schaffer":{"currentFile":{"count":1,"lastUpdated":1743470744584}}},"Externality":{"Externality":{"currentFile":{"count":3,"lastUpdated":1743520583320}}},"turned":{"turned":{"currentFile":{"count":1,"lastUpdated":1743471109279}}},"Bliss":{"Bliss":{"currentFile":{"count":1,"lastUpdated":1743471117244}}},"mechanics":{"mechanics":{"currentVault":{"count":1,"lastUpdated":1743471396741}}},"escape":{"escape":{"currentVault":{"count":1,"lastUpdated":1743472070588}}},"Another":{"Another":{"currentFile":{"count":1,"lastUpdated":1743473584168}}},"variant":{"variant":{"currentVault":{"count":1,"lastUpdated":1743518326609}}},"externality":{"externality":{"currentFile":{"count":3,"lastUpdated":1743533006033}}},"Overdetermination":{"Overdetermination":{"currentVault":{"count":1,"lastUpdated":1743520612438}}},"overdetermination":{"overdetermination":{"currentFile":{"count":9,"lastUpdated":1743523059823}}},"priority":{"priority":{"currentFile":{"count":4,"lastUpdated":1743560993016}}},"singleton":{"singleton":{"currentFile":{"count":1,"lastUpdated":1743523086689}}},"socrates":{"socrates":{"currentFile":{"count":1,"lastUpdated":1743523088611}}},"never-ending":{"never-ending":{"currentVault":{"count":1,"lastUpdated":1743528780743}}},"satisfying":{"satisfying":{"currentVault":{"count":2,"lastUpdated":1743908755618}}},"kind-instantiation":{"kind-instantiation":{"currentFile":{"count":2,"lastUpdated":1743533020368}}},"forever":{"forever":{"currentVault":{"count":1,"lastUpdated":1743533123315}}},"Dummy":{"Dummy":{"currentVault":{"count":1,"lastUpdated":1743535167797}}},"substantive":{"substantive":{"currentFile":{"count":1,"lastUpdated":1743535184081}}},"criteria":{"criteria":{"currentVault":{"count":1,"lastUpdated":1743535194147}}},"dummy":{"dummy":{"currentFile":{"count":2,"lastUpdated":1743535564811}}},"defect":{"defect":{"currentVault":{"count":1,"lastUpdated":1743535717542}}},"Something":{"Something":{"currentFile":{"count":1,"lastUpdated":1743536204255}}},"covering":{"covering":{"currentFile":{"count":1,"lastUpdated":1743536381393}}},"substantial":{"substantial":{"currentFile":{"count":1,"lastUpdated":1743536573833}}},"Coherentism":{"Coherentism":{"currentFile":{"count":1,"lastUpdated":1743536603494}}},"anti-symmetric":{"anti-symmetric":{"currentVault":{"count":1,"lastUpdated":1743536807120}}},"coherentism":{"coherentism":{"currentFile":{"count":4,"lastUpdated":1743559053220}}},"symmetry":{"symmetry":{"currentVault":{"count":2,"lastUpdated":1743891413432}}},"symmetric":{"symmetric":{"currentVault":{"count":2,"lastUpdated":1743891399391}}},"reflexive":{"reflexive":{"currentVault":{"count":2,"lastUpdated":1743891566446}}},"buddist":{"buddist":{"currentVault":{"count":1,"lastUpdated":1743537053095}}},"ignore":{"ignore":{"currentVault":{"count":1,"lastUpdated":1743558707491}}},"magnetic":{"magnetic":{"currentVault":{"count":1,"lastUpdated":1743558990807}}},"transitivity":{"transitivity":{"currentVault":{"count":2,"lastUpdated":1743891016886}}},"temperal":{"temperal":{"currentVault":{"count":2,"lastUpdated":1744774518770}}},"self-identity":{"self-identity":{"currentVault":{"count":1,"lastUpdated":1743561213454}}},"anti-fundamentalism":{"anti-fundamentalism":{"currentFile":{"count":1,"lastUpdated":1743561477760}}},"mutation":{"mutation":{"currentVault":{"count":1,"lastUpdated":1743888578455}}},"mutually":{"mutually":{"currentVault":{"count":1,"lastUpdated":1743888581853}}},"biconditional":{"biconditional":{"currentFile":{"count":1,"lastUpdated":1743891021179}}},"accordance":{"accordance":{"currentVault":{"count":1,"lastUpdated":1743898975120}}},"Inductive":{"Inductive":{"currentVault":{"count":1,"lastUpdated":1743899025706}}},"deriving":{"deriving":{"currentFile":{"count":2,"lastUpdated":1743905832725}}},"recursive":{"recursive":{"currentVault":{"count":1,"lastUpdated":1743905691618}}},"induct":{"induct":{"currentVault":{"count":1,"lastUpdated":1743905716567}}},"reformulate":{"reformulate":{"currentVault":{"count":1,"lastUpdated":1743906338405}}},"antecedent":{"antecedent":{"currentVault":{"count":2,"lastUpdated":1743907944851}}},"absurdity":{"absurdity":{"currentFile":{"count":1,"lastUpdated":1743908737923}}},"$Val^M":{"$Val^M":{"currentVault":{"count":1,"lastUpdated":1743917713929}}},"extensionality":{"extensionality":{"currentFile":{"count":1,"lastUpdated":1744774124204}}},"anthropic":{"anthropic":{"currentFile":{"count":1,"lastUpdated":1744774371327}}},"Goliath":{"Goliath":{"currentFile":{"count":8,"lastUpdated":1744775121624}}},"properties":{"properties":{"currentFile":{"count":2,"lastUpdated":1744774744041}}},"Lumpl":{"Lumpl":{"currentFile":{"count":2,"lastUpdated":1744774934778}}},"survive":{"survive":{"currentVault":{"count":3,"lastUpdated":1744774790105}}},"counterpart":{"counterpart":{"currentVault":{"count":1,"lastUpdated":1744774780321}}},"Strategy":{"Strategy":{"currentFile":{"count":1,"lastUpdated":1744775142200}}},"Eliminativist":{"Eliminativist":{"currentFile":{"count":1,"lastUpdated":1744775175201}}},"ordinary":{"ordinary":{"currentVault":{"count":2,"lastUpdated":1744776286174}}},"statue":{"statue":{"currentFile":{"count":2,"lastUpdated":1744775927679}}},"incompatible":{"incompatible":{"currentVault":{"count":1,"lastUpdated":1744775400130}}},"Inwagen":{"Inwagen":{"currentVault":{"count":1,"lastUpdated":1744775426592}}},"creature":{"creature":{"currentFile":{"count":1,"lastUpdated":1744775683444}}},"first":{"first":{"currentVault":{"count":1,"lastUpdated":1744775718925}}},"essential":{"essential":{"currentVault":{"count":1,"lastUpdated":1744775774850}}},"Consequent":{"Consequent":{"currentVault":{"count":1,"lastUpdated":1744775894033}}},"identity":{"identity":{"currentFile":{"count":2,"lastUpdated":1744776340874}}},"similarity":{"similarity":{"currentVault":{"count":1,"lastUpdated":1744776328803}}},"Dominant":{"Dominant":{"currentFile":{"count":1,"lastUpdated":1744776511057}}}}